yapfm/__init__.py
yapfm/cache/__init__.py
yapfm/cache/lazy_loading.py
yapfm/cache/smart_cache.py
yapfm/cache/streaming_reader.py
yapfm/cache/types.py
yapfm/decorators.py
yapfm/exceptions/__init__.py
yapfm/exceptions/file_manager_error.py
yapfm/exceptions/file_operations.py
yapfm/helpers/__init__.py
yapfm/helpers/dict_utils.py
yapfm/helpers/io.py
yapfm/helpers/toml_merger.py
yapfm/helpers/utils.py
yapfm/helpers/validation.py
yapfm/manager.py
yapfm/mixins/__init__.py
yapfm/mixins/analysis_mixin.py
yapfm/mixins/cache_mixin.py
yapfm/mixins/cleanup_mixin.py
yapfm/mixins/clone_mixin.py
yapfm/mixins/context_mixin.py
yapfm/mixins/export_mixin.py
yapfm/mixins/file_operations_mixin.py
yapfm/mixins/key_operations_mixin.py
yapfm/mixins/lazy_sections_mixin.py
yapfm/mixins/multi_file_mixin.py
yapfm/mixins/search_mixin.py
yapfm/mixins/section_operations_mixin.py
yapfm/mixins/security_mixin.py
yapfm/mixins/streaming_mixin.py
yapfm/mixins/transform_mixin.py
yapfm/multi_file/__init__.py
yapfm/multi_file/loader.py
yapfm/multi_file/merge_strategies/__init__.py
yapfm/multi_file/merge_strategies/append.py
yapfm/multi_file/merge_strategies/base.py
yapfm/multi_file/merge_strategies/conditional.py
yapfm/multi_file/merge_strategies/deep.py
yapfm/multi_file/merge_strategies/namespace.py
yapfm/multi_file/merge_strategies/priority.py
yapfm/multi_file/merge_strategies/replace.py
yapfm/multi_file/strategies.py
yapfm/proxy.py
yapfm/registry.py
yapfm/strategies/__init__.py
yapfm/strategies/base.py
yapfm/strategies/json_strategy.py
yapfm/strategies/toml_strategy.py
yapfm/strategies/yaml_strategy.py
yapfm-0.5.0.dist-info/LICENSE
yapfm-0.5.0.dist-info/METADATA
yapfm-0.5.0.dist-info/WHEEL
yapfm-0.5.0.dist-info/RECORD
