Metadata-Version: 2.3
Name: yapfm
Version: 0.5.0
Summary: Yet Another Python File Manager
Author: Ephraim Seddor
Author-email: seddorephraim7@gmail.com
Requires-Python: >=3.10,<3.14
Classifier: Programming Language :: Python :: 3
Classifier: Programming Language :: Python :: 3.10
Classifier: Programming Language :: Python :: 3.11
Classifier: Programming Language :: Python :: 3.12
Classifier: Programming Language :: Python :: 3.13
Requires-Dist: pyyaml (>=6.0.2,<7.0.0)
Requires-Dist: regman (>=0.2.0,<0.3.0)
Requires-Dist: tomlkit (>=0.13.3,<0.14.0)
